{
  "name": "快雪时晴帖",
  "dynasty": "魏晉南北朝",
  "author": "王羲之",
  "year": -1,
  "calligraphy_type": "其他",
  "source": "Marvis per_stele 数据集 (id=86)",
  "editor": "marvis-import-v2",
  "release_date": "2024-12-01",
  "description": "类型：行书尺牍（唐摹本）。原始朝代：东晋。作者：王羲之。共4行28字，王羲之行书尺牍，唐摹本，纸本墨迹，纵23cm横14.8cm，现藏台北故宫博物院。乾隆皇帝将其与王献之《中秋帖》、王珣《伯远帖》合称'三希'，置于养心殿三希堂，为三希之首，题'神乎技矣'、'天下无双，古今鲜对'等。全帖或行或楷，笔致圆劲古雅，节奏从容。乾隆皇帝前后共题跋71则，可见其珍爱之深。此帖是大雪初晴时以愉快心情写给朋友'山阴张侯'的问候信札，被誉为'二十八骊珠'。",
  "content": "羲之叩首。一场快雪过后天气放晴，心情甚好。想来您也平安安好。事情未能如愿，心中郁结。身体精力不济，不多写了。王羲之叩首。山阴张侯收。",
  "original_text": "羲之顿首。快雪时晴，佳。想安善。未果为结。力不次。王羲之顿首。山阴张侯。",
  "translation": "羲之叩首。一场快雪过后天气放晴，心情甚好。想来您也平安安好。事情未能如愿，心中郁结。身体精力不济，不多写了。王羲之叩首。山阴张侯收。",
  "note": "共4行28字，王羲之行书尺牍，唐摹本，纸本墨迹，纵23cm横14.8cm，现藏台北故宫博物院。乾隆皇帝将其与王献之《中秋帖》、王珣《伯远帖》合称'三希'，置于养心殿三希堂，为三希之首，题'神乎技矣'、'天下无双，古今鲜对'等。全帖或行或楷，笔致圆劲古雅，节奏从容。乾隆皇帝前后共题跋71则，可见其珍爱之深。此帖是大雪初晴时以愉快心情写给朋友'山阴张侯'的问候信札，被誉为'二十八骊珠'。",
  "raw_type": "行书尺牍（唐摹本）",
  "raw_dynasty": "东晋",
  "marvis_id": 86
}
