{
  "name": "淡墨秋山诗帖",
  "dynasty": "宋遼金",
  "author": "米芾",
  "year": -1,
  "calligraphy_type": "其他",
  "source": "Marvis per_stele 数据集 (id=421)",
  "editor": "marvis-import-v2",
  "release_date": "2024-12-01",
  "description": "类型：墨迹（诗帖）。原始朝代：北宋。作者：米芾。此帖以淡墨书写，与米芾常见的浓墨作品不同，更显清雅飘逸，意趣高远。\n[核查修正·verify_beisong_mi2_report] 末句库内作'理乱绳头一万年'，权威本（故宫博物院藏，收入《墨缘汇观》《三希堂法帖》）为'不到平山谩五年'，末句全错；释译'酒边欢聚'亦属臆解，须补全并改正释译。",
  "content": "以淡墨般的笔意勾画远天秋山，暮霞回照为紫烟添彩。故人安好，期盼再度携手；算来已整整五年未到平山一游了。",
  "original_text": "淡墨秋山画远天，暮霞还照紫添烟。\n故人好在重携手，不到平山谩五年。",
  "translation": "以淡墨般的笔意勾画远天秋山，暮霞回照为紫烟添彩。故人安好，期盼再度携手；算来已整整五年未到平山一游了。",
  "note": "此帖以淡墨书写，与米芾常见的浓墨作品不同，更显清雅飘逸，意趣高远。\n[核查修正·verify_beisong_mi2_report] 末句库内作'理乱绳头一万年'，权威本（故宫博物院藏，收入《墨缘汇观》《三希堂法帖》）为'不到平山谩五年'，末句全错；释译'酒边欢聚'亦属臆解，须补全并改正释译。",
  "raw_type": "墨迹（诗帖）",
  "raw_dynasty": "北宋",
  "marvis_id": 421
}
