{
  "name": "黄州寒食诗卷跋",
  "dynasty": "宋遼金",
  "author": "黄庭坚",
  "year": -1,
  "calligraphy_type": "其他",
  "source": "Marvis per_stele 数据集 (id=270)",
  "editor": "marvis-import-v2",
  "release_date": "2024-12-01",
  "description": "类型：墨迹（题跋）。原始朝代：北宋。作者：黄庭坚。黄庭坚为苏轼《黄州寒食帖》所书跋语，是中国书法史上最著名的题跋之一。黄庭坚在跋中对苏轼的诗歌和书法都给予了极高评价，用词精当，眼光精准。跋文本身也是黄庭坚行书的精品，与苏轼《黄州寒食帖》正文相得益彰，被称为\"双璧\"——一文一书皆为万世珍品。此跋现与《黄州寒食帖》同藏台北故宫博物院。",
  "content": "东坡这两首诗像李白的诗，恐怕李白也有未到之处。这书法兼有颜真卿、杨凝式、李建中三家的笔意，就算让东坡再写一遍，也未必能达到这个水平。……",
  "original_text": "黄州寒食诗卷跋\n\n东坡此诗似李太白，犹恐太白有未到处。此书兼颜鲁公、杨少师、李西台笔意。爱使笔所，是其病处。试使东坡复为之，未必及此。它日东坡或见此书，应笑我于无佛处称尊也。",
  "translation": "东坡这两首诗像李白的诗，恐怕李白也有未到之处。这书法兼有颜真卿、杨凝式、李建中三家的笔意，就算让东坡再写一遍，也未必能达到这个水平。……",
  "note": "黄庭坚为苏轼《黄州寒食帖》所书跋语，是中国书法史上最著名的题跋之一。黄庭坚在跋中对苏轼的诗歌和书法都给予了极高评价，用词精当，眼光精准。跋文本身也是黄庭坚行书的精品，与苏轼《黄州寒食帖》正文相得益彰，被称为\"双璧\"——一文一书皆为万世珍品。此跋现与《黄州寒食帖》同藏台北故宫博物院。",
  "raw_type": "墨迹（题跋）",
  "raw_dynasty": "北宋",
  "marvis_id": 270
}
