{
  "name": "潭帖",
  "dynasty": "宋遼金",
  "author": "佚名",
  "year": 1043,
  "calligraphy_type": "其他",
  "source": "Marvis per_stele 数据集 (id=252)",
  "editor": "marvis-import-v2",
  "release_date": "2024-12-01",
  "description": "类型：刻帖（丛帖）。原始朝代：北宋。作者：佚名。刻于宋庆历三年（1043年），在长沙（古称潭州）刊刻，故称《潭帖》。以《淳化阁帖》为基础增删而成，是宋代早期私刻丛帖的重要代表。因其刊刻时间早于《绛帖》《汝帖》，在丛帖史上具有开创性地位。",
  "content": "（《潭帖》为长沙刊刻，在《淳化阁帖》基础上增补了一些法书。）",
  "original_text": "（《潭帖》为宋代长沙刻帖，以《淳化阁帖》为基础，补充了一些未收的法书。是宋代重要的私刻丛帖之一。）",
  "translation": "（《潭帖》为长沙刊刻，在《淳化阁帖》基础上增补了一些法书。）",
  "note": "刻于宋庆历三年（1043年），在长沙（古称潭州）刊刻，故称《潭帖》。以《淳化阁帖》为基础增删而成，是宋代早期私刻丛帖的重要代表。因其刊刻时间早于《绛帖》《汝帖》，在丛帖史上具有开创性地位。",
  "raw_type": "刻帖（丛帖）",
  "raw_dynasty": "北宋",
  "marvis_id": 252
}
