{
  "name": "行书联（刘墉书）",
  "dynasty": "元明清",
  "author": "刘墉",
  "year": -1,
  "calligraphy_type": "其他",
  "source": "Marvis per_stele 数据集 (id=571)",
  "editor": "marvis-import-v2",
  "release_date": "2024-12-01",
  "description": "类型：清行书联。原始朝代：清。作者：刘墉。清刘墉（1719—1804）字崇如，号石庵，山东诸城人，乾隆名臣，与翁方纲、王文治、梁同书并称清四家，行书丰腴浑厚，世称「浓墨宰相」。来源：博物馆著录、网易、凤凰网交叉核对。原文为传世联语，版本或有异文，标注参考。",
  "content": "窗外含着竹影，清雅如此；人比梅花还要清瘦几分。\n（刘墉以丰腴浑厚的行书写此七言联，世称「浓墨宰相」。此为其常见传世联语之一）",
  "original_text": "窗含竹影清如许，人比梅花瘦几分。\n（刘墉行书七言联，用丰腴浑厚之笔，世称「浓墨宰相」。此为其常见传世联语之一）",
  "translation": "窗外含着竹影，清雅如此；人比梅花还要清瘦几分。\n（刘墉以丰腴浑厚的行书写此七言联，世称「浓墨宰相」。此为其常见传世联语之一）",
  "note": "清刘墉（1719—1804）字崇如，号石庵，山东诸城人，乾隆名臣，与翁方纲、王文治、梁同书并称清四家，行书丰腴浑厚，世称「浓墨宰相」。来源：博物馆著录、网易、凤凰网交叉核对。原文为传世联语，版本或有异文，标注参考。",
  "raw_type": "清行书联",
  "raw_dynasty": "清",
  "marvis_id": 571
}
